bzapi/__init__.py
bzapi/api_client.py
bzapi/api_response.py
bzapi/configuration.py
bzapi/examples.py
bzapi/exceptions.py
bzapi/py.typed
bzapi/rest.py
bzapi/syncapi.py
bzapi/api/__init__.py
bzapi/api/default_api.py
bzapi/models/__init__.py
bzapi/models/box.py
bzapi/models/chat.py
bzapi/models/chat_block_reference.py
bzapi/models/chat_conversation_block.py
bzapi/models/data_extraction.py
bzapi/models/data_extraction_request.py
bzapi/models/database.py
bzapi/models/database_analytics_request.py
bzapi/models/database_analytics_response.py
bzapi/models/database_connection.py
bzapi/models/database_record.py
bzapi/models/database_record_fields_value.py
bzapi/models/database_source_table.py
bzapi/models/database_table_column_spec.py
bzapi/models/document.py
bzapi/models/error.py
bzapi/models/file_reference.py
bzapi/models/list_database_records_request.py
bzapi/models/sigma_filter_parameters.py
bzapi/models/sigma_sort_parameters.py
bzapi/models/source.py
bzapi/models/span.py
bzapi/models/v2_databases_database_id_records_list_post200_response.py
bzapi/models/web_reference.py
bzapi-0.0.1.dist-info/METADATA
bzapi-0.0.1.dist-info/WHEEL
bzapi-0.0.1.dist-info/licenses/LICENSE
bzapi-0.0.1.dist-info/RECORD
